cascadeflow/__init__.py
cascadeflow/agent.py
cascadeflow/config_loader.py
cascadeflow/core/__init__.py
cascadeflow/core/batch.py
cascadeflow/core/batch_config.py
cascadeflow/core/cascade.py
cascadeflow/core/execution.py
cascadeflow/dynamic_config/__init__.py
cascadeflow/dynamic_config/manager.py
cascadeflow/dynamic_config/watcher.py
cascadeflow/guardrails/__init__.py
cascadeflow/guardrails/content_moderator.py
cascadeflow/guardrails/manager.py
cascadeflow/guardrails/pii_detector.py
cascadeflow/integrations/__init__.py
cascadeflow/integrations/litellm.py
cascadeflow/integrations/otel.py
cascadeflow/integrations/langchain/__init__.py
cascadeflow/integrations/langchain/complexity.py
cascadeflow/integrations/langchain/cost_tracking.py
cascadeflow/integrations/langchain/langchain_callbacks.py
cascadeflow/integrations/langchain/models.py
cascadeflow/integrations/langchain/types.py
cascadeflow/integrations/langchain/utils.py
cascadeflow/integrations/langchain/wrapper.py
cascadeflow/integrations/langchain/routers/__init__.py
cascadeflow/integrations/langchain/routers/base.py
cascadeflow/integrations/langchain/routers/pre_router.py
cascadeflow/integrations/langchain/tests/__init__.py
cascadeflow/integrations/langchain/tests/test_langchain_callbacks.py
cascadeflow/integrations/langchain/tests/test_langchain_tools.py
cascadeflow/interface/__init__.py
cascadeflow/interface/visual_consumer.py
cascadeflow/limits/__init__.py
cascadeflow/limits/rate_limiter.py
cascadeflow/ml/__init__.py
cascadeflow/ml/embedding.py
cascadeflow/profiles/__init__.py
cascadeflow/profiles/profile_manager.py
cascadeflow/profiles/tier_config.py
cascadeflow/profiles/user_profile.py
cascadeflow/providers/__init__.py
cascadeflow/providers/anthropic.py
cascadeflow/providers/base.py
cascadeflow/providers/deepseek.py
cascadeflow/providers/groq.py
cascadeflow/providers/huggingface.py
cascadeflow/providers/ollama.py
cascadeflow/providers/openai.py
cascadeflow/providers/openrouter.py
cascadeflow-0.6.5.dist-info/licenses/LICENSE
cascadeflow-0.6.5.dist-info/METADATA
cascadeflow-0.6.5.dist-info/WHEEL
cascadeflow-0.6.5.dist-info/top_level.txt
cascadeflow-0.6.5.dist-info/RECORD
