Metadata-Version: 2.4
Name: cascadeflow
Version: 0.6.5
Summary: Smart AI model cascading for cost optimization - Save 40-85% on LLM costs with 2-6x faster responses. Available for Python and TypeScript/JavaScript.
Author-email: "Lemony Inc." <hello@lemony.ai>
Maintainer-email: "Lemony Inc." <hello@lemony.ai>
License: MIT
Project-URL: Homepage, https://lemony.ai
Project-URL: Documentation, https://github.com/lemony-ai/cascadeflow
Project-URL: Repository, https://github.com/lemony-ai/cascadeflow
Project-URL: Bug Tracker, https://github.com/lemony-ai/cascadeflow/issues
Project-URL: Changelog, https://github.com/lemony-ai/cascadeflow/blob/main/CHANGELOG.md
Keywords: ai,llm,cost-optimization,model-routing,cascade,inference,openai,anthropic,gpt,claude,machine-learning,groq,typescript,javascript,browser,edge-functions
Classifier: Development Status :: 4 - Beta
Classifier: Intended Audience :: Developers
Classifier: License :: OSI Approved :: MIT License
Classifier: Programming Language :: Python :: 3
Classifier: Programming Language :: Python :: 3.9
Classifier: Programming Language :: Python :: 3.10
Classifier: Programming Language :: Python :: 3.11
Classifier: Programming Language :: Python :: 3.12
Classifier: Topic :: Software Development :: Libraries :: Python Modules
Classifier: Topic :: Scientific/Engineering :: Artificial Intelligence
Classifier: Operating System :: OS Independent
Requires-Python: >=3.9
License-File: LICENSE
Requires-Dist: pydantic>=2.0.0
Requires-Dist: httpx>=0.25.0
Requires-Dist: tiktoken>=0.5.0
Requires-Dist: rich>=13.0.0
Provides-Extra: openai
Requires-Dist: openai>=1.0.0; extra == "openai"
Provides-Extra: anthropic
Requires-Dist: anthropic>=0.8.0; extra == "anthropic"
Provides-Extra: groq
Requires-Dist: groq>=0.4.0; extra == "groq"
Provides-Extra: huggingface
Requires-Dist: huggingface-hub>=0.19.0; extra == "huggingface"
Provides-Extra: together
Requires-Dist: together>=0.2.0; extra == "together"
Provides-Extra: vllm
Requires-Dist: vllm>=0.2.0; extra == "vllm"
Provides-Extra: providers
Requires-Dist: openai>=1.0.0; extra == "providers"
Requires-Dist: anthropic>=0.8.0; extra == "providers"
Requires-Dist: groq>=0.4.0; extra == "providers"
Provides-Extra: local
Requires-Dist: vllm>=0.2.0; extra == "local"
Provides-Extra: semantic
Requires-Dist: sentence-transformers>=2.2.0; extra == "semantic"
Requires-Dist: fastembed>=0.2.0; extra == "semantic"
Provides-Extra: dev
Requires-Dist: pytest>=7.4.0; extra == "dev"
Requires-Dist: pytest-asyncio>=0.21.0; extra == "dev"
Requires-Dist: pytest-cov>=4.1.0; extra == "dev"
Requires-Dist: pytest-mock>=3.12.0; extra == "dev"
Requires-Dist: python-dotenv>=1.0.0; extra == "dev"
Requires-Dist: fastembed>=0.2.0; extra == "dev"
Requires-Dist: black>=23.0.0; extra == "dev"
Requires-Dist: ruff>=0.1.0; extra == "dev"
Requires-Dist: mypy>=1.5.0; extra == "dev"
Requires-Dist: isort>=5.12.0; extra == "dev"
Requires-Dist: pre-commit>=3.5.0; extra == "dev"
Requires-Dist: rich>=13.0.0; extra == "dev"
Requires-Dist: python-dotenv>=1.0.0; extra == "dev"
Provides-Extra: docs
Requires-Dist: mkdocs>=1.5.0; extra == "docs"
Requires-Dist: mkdocs-material>=9.4.0; extra == "docs"
Requires-Dist: mkdocstrings[python]>=0.23.0; extra == "docs"
Provides-Extra: all
Requires-Dist: openai>=1.0.0; extra == "all"
Requires-Dist: anthropic>=0.8.0; extra == "all"
Requires-Dist: groq>=0.4.0; extra == "all"
Requires-Dist: huggingface-hub>=0.19.0; extra == "all"
Requires-Dist: together>=0.2.0; extra == "all"
Requires-Dist: vllm>=0.2.0; extra == "all"
Requires-Dist: sentence-transformers>=2.2.0; extra == "all"
Requires-Dist: fastembed>=0.2.0; extra == "all"
Dynamic: license-file
